{
  "id": "lm-000271",
  "title": "元元理論的最小結構",
  "source_file": "content/papers/2026/2026-05/元元理論的最小結構.md",
  "legacy_slug": "paper-195.md",
  "ext": "md",
  "language": "zh-Hant",
  "created": "2026-05-31",
  "year": 2026,
  "month": "2026-05",
  "date_confidence": "explicit",
  "date_basis": "git-first-add (publication/upload date; not the author's in-text writing date)",
  "canonical_url": "/p/lm-000271/",
  "raw_url": "/raw/lm-000271.md",
  "api_url": "/api/papers/lm-000271.json",
  "legacy_page_url": "/papers/paper-195.md.html",
  "legacy_raw_url": "/papers/paper-195.md",
  "hash": "sha256:c629adb378aeb74794b6a4224bd952246519f34f716c9353a82089b715db8bd7"
}
