{
  "id": "lm-000171",
  "title": "《作者已死：一個自我證明的悖論——或者說，我如何不讀原著就論證了巴特》",
  "source_file": "content/papers/2026/2026-05/《作者已死：一個自我證明的悖論——或者說，我如何不讀原著就論證了巴特》.md",
  "legacy_slug": "paper-148.md",
  "ext": "md",
  "language": "zh-Hant",
  "created": "2026-05-20",
  "year": 2026,
  "month": "2026-05",
  "date_confidence": "explicit",
  "date_basis": "git-first-add (publication/upload date; not the author's in-text writing date)",
  "canonical_url": "/p/lm-000171/",
  "raw_url": "/raw/lm-000171.md",
  "api_url": "/api/papers/lm-000171.json",
  "legacy_page_url": "/papers/paper-148.md.html",
  "legacy_raw_url": "/papers/paper-148.md",
  "hash": "sha256:4a4d5e52ce904dd08447944e225210f4ed25bfe76c1046f31cef66792774dc89"
}
