{
  "id": "lm-001013",
  "title": "貨幣的編織本體論：交換場的無限維結構與相變測不準原理",
  "source_file": "content/papers/2026/2026-06/貨幣的編織本體論：交換場的無限維結構與相變測不準原理.md",
  "legacy_slug": "paper-1048.md",
  "ext": "md",
  "language": "zh-Hant",
  "created": "2026-06-25",
  "year": 2026,
  "month": "2026-06",
  "date_confidence": "explicit",
  "date_basis": "git-first-add (publication/upload date; not the author's in-text writing date)",
  "canonical_url": "/p/lm-001013/",
  "raw_url": "/raw/lm-001013.md",
  "api_url": "/api/papers/lm-001013.json",
  "legacy_page_url": "/papers/paper-1048.md.html",
  "legacy_raw_url": "/papers/paper-1048.md",
  "hash": "sha256:bd48ce7536021d3eae4884262c652fee59bfce98273293c273af74afdca55587"
}
