{
  "id": "lm-000177",
  "title": "《從量化到物化：社會系統的情感失真與倫理崩潰》",
  "source_file": "content/papers/2026/2026-05/《從量化到物化：社會系統的情感失真與倫理崩潰》.md",
  "legacy_slug": "paper-152.md",
  "ext": "md",
  "language": "zh-Hant",
  "created": "2026-05-14",
  "year": 2026,
  "month": "2026-05",
  "date_confidence": "explicit",
  "date_basis": "git-first-add (publication/upload date; not the author's in-text writing date)",
  "canonical_url": "/p/lm-000177/",
  "raw_url": "/raw/lm-000177.md",
  "api_url": "/api/papers/lm-000177.json",
  "legacy_page_url": "/papers/paper-152.md.html",
  "legacy_raw_url": "/papers/paper-152.md",
  "hash": "sha256:14fdee9340b61ab1773be771744357303deebf692a9c93a430c68470ccbcdc6f"
}
