{
  "id": "lm-001103",
  "title": "附錄：2026年6月5日的觀察備忘",
  "source_file": "content/papers/2026/2026-06/附錄：2026年6月5日的觀察備忘.md",
  "legacy_slug": "202665.md",
  "ext": "md",
  "language": "zh-Hant",
  "created": "2026-06-17",
  "year": 2026,
  "month": "2026-06",
  "date_confidence": "explicit",
  "date_basis": "git-first-add (publication/upload date; not the author's in-text writing date)",
  "canonical_url": "/p/lm-001103/",
  "raw_url": "/raw/lm-001103.md",
  "api_url": "/api/papers/lm-001103.json",
  "legacy_page_url": "/papers/202665.md.html",
  "legacy_raw_url": "/papers/202665.md",
  "hash": "sha256:3b5896afba4ae597834085c84558d8182c4a149b55b4eb6baeae7c0747348588"
}
