{
  "id": "lm-000244",
  "title": "主體之裂：概率性存在的崛起與這個奇特時代的本體論觀察",
  "source_file": "content/papers/2026/2026-06/主體之裂：概率性存在的崛起與這個奇特時代的本體論觀察.md",
  "legacy_slug": "paper-557.md",
  "ext": "md",
  "language": "zh-Hant",
  "created": "2026-06-20",
  "year": 2026,
  "month": "2026-06",
  "date_confidence": "explicit",
  "date_basis": "git-first-add (publication/upload date; not the author's in-text writing date)",
  "canonical_url": "/p/lm-000244/",
  "raw_url": "/raw/lm-000244.md",
  "api_url": "/api/papers/lm-000244.json",
  "legacy_page_url": "/papers/paper-557.md.html",
  "legacy_raw_url": "/papers/paper-557.md",
  "hash": "sha256:8e90d8d8dc4e6c27bfb461a064e10b800d44eb0623285b76f4fe2b9dd8cff03c"
}
