{
  "id": "lm-000409",
  "title": "多重宇宙修仙世界觀設定",
  "source_file": "content/papers/2026/2026-05/多重宇宙修仙世界觀設定.md",
  "legacy_slug": "paper-225.md",
  "ext": "md",
  "language": "zh-Hant",
  "created": "2026-05-21",
  "year": 2026,
  "month": "2026-05",
  "date_confidence": "explicit",
  "date_basis": "git-first-add (publication/upload date; not the author's in-text writing date)",
  "canonical_url": "/p/lm-000409/",
  "raw_url": "/raw/lm-000409.md",
  "api_url": "/api/papers/lm-000409.json",
  "legacy_page_url": "/papers/paper-225.md.html",
  "legacy_raw_url": "/papers/paper-225.md",
  "hash": "sha256:a716909e1c5c022a3391be186e503562d3db588832dcff99c269fbf16ab64cf4"
}
