{
  "id": "lm-000608",
  "title": "數學的七層完備性標準：相變點分佈層與理論演化的測不準原理",
  "source_file": "content/papers/2026/2026-06/數學的七層完備性標準：相變點分佈層與理論演化的測不準原理.md",
  "legacy_slug": "paper-801.md",
  "ext": "md",
  "language": "zh-Hant",
  "created": "2026-06-25",
  "year": 2026,
  "month": "2026-06",
  "date_confidence": "explicit",
  "date_basis": "git-first-add (publication/upload date; not the author's in-text writing date)",
  "canonical_url": "/p/lm-000608/",
  "raw_url": "/raw/lm-000608.md",
  "api_url": "/api/papers/lm-000608.json",
  "legacy_page_url": "/papers/paper-801.md.html",
  "legacy_raw_url": "/papers/paper-801.md",
  "hash": "sha256:1f57a5df2fae9ce307030fcafe6212b8ecd780e044cbd474da8c5e483b00c880"
}
