{
  "id": "lm-001154",
  "title": "高階本體收斂論：概念作為無限展開、無限連接與無限收斂的三重動態結構",
  "source_file": "content/papers/2026/2026-06/高階本體收斂論：概念作為無限展開、無限連接與無限收斂的三重動態結構.md",
  "legacy_slug": "paper-1135.md",
  "ext": "md",
  "language": "zh-Hant",
  "created": "2026-06-23",
  "year": 2026,
  "month": "2026-06",
  "date_confidence": "explicit",
  "date_basis": "git-first-add (publication/upload date; not the author's in-text writing date)",
  "canonical_url": "/p/lm-001154/",
  "raw_url": "/raw/lm-001154.md",
  "api_url": "/api/papers/lm-001154.json",
  "legacy_page_url": "/papers/paper-1135.md.html",
  "legacy_raw_url": "/papers/paper-1135.md",
  "hash": "sha256:9caa6a7cf6d99f819db6b1875c22833e470bb5efa8e3142bffe13252a9c53c4a"
}
