{
  "id": "lm-000855",
  "title": "算子先於值_APL算子代數的類型多態重建與算子本體論的實驗性確認",
  "source_file": "content/papers/2026/2026-06/算子先於值_APL算子代數的類型多態重建與算子本體論的實驗性確認.md",
  "legacy_slug": "APL.md",
  "ext": "md",
  "language": "zh-Hant",
  "created": "2026-06-18",
  "year": 2026,
  "month": "2026-06",
  "date_confidence": "explicit",
  "date_basis": "git-first-add (publication/upload date; not the author's in-text writing date)",
  "canonical_url": "/p/lm-000855/",
  "raw_url": "/raw/lm-000855.md",
  "api_url": "/api/papers/lm-000855.json",
  "legacy_page_url": "/papers/APL.md.html",
  "legacy_raw_url": "/papers/APL.md",
  "hash": "sha256:0da8253c58cee5a34853363e40ee77212d575ce346eaa786bb10874ea722e6c2"
}
