{
  "id": "lm-000703",
  "title": "注意力市場作為極限張力結構的工程實證",
  "source_file": "content/papers/2026/2026-06/注意力市場作為極限張力結構的工程實證.md",
  "legacy_slug": "paper-858.md",
  "ext": "md",
  "language": "zh-Hant",
  "created": "2026-06-01",
  "year": 2026,
  "month": "2026-06",
  "date_confidence": "explicit",
  "date_basis": "git-first-add (publication/upload date; not the author's in-text writing date)",
  "canonical_url": "/p/lm-000703/",
  "raw_url": "/raw/lm-000703.md",
  "api_url": "/api/papers/lm-000703.json",
  "legacy_page_url": "/papers/paper-858.md.html",
  "legacy_raw_url": "/papers/paper-858.md",
  "hash": "sha256:fb58b283bb86d4be9e6388ba80ec775acdd30004cbe23b52d17b7903f3ac6637"
}
