{
  "id": "lm-000656",
  "title": "有一個國家曾承諾天堂：蘇聯與共產主義過渡敘事的終極困境",
  "source_file": "content/papers/2026/2026-06/有一個國家曾承諾天堂：蘇聯與共產主義過渡敘事的終極困境.md",
  "legacy_slug": "paper-827.md",
  "ext": "md",
  "language": "zh-Hant",
  "created": "2026-06-26",
  "year": 2026,
  "month": "2026-06",
  "date_confidence": "explicit",
  "date_basis": "git-first-add (publication/upload date; not the author's in-text writing date)",
  "canonical_url": "/p/lm-000656/",
  "raw_url": "/raw/lm-000656.md",
  "api_url": "/api/papers/lm-000656.json",
  "legacy_page_url": "/papers/paper-827.md.html",
  "legacy_raw_url": "/papers/paper-827.md",
  "hash": "sha256:96c8974d1432e0d8b3a7e4ef36c1226350498f0ce4b9d4a704a88ab0a705882d"
}
