{
  "id": "lm-000188",
  "title": "《永恆輪迴：魔法科技循環史》",
  "source_file": "content/papers/2026/2026-05/《永恆輪迴：魔法科技循環史》.md",
  "legacy_slug": "paper-161.md",
  "ext": "md",
  "language": "zh-Hant",
  "created": "2026-05-21",
  "year": 2026,
  "month": "2026-05",
  "date_confidence": "explicit",
  "date_basis": "git-first-add (publication/upload date; not the author's in-text writing date)",
  "canonical_url": "/p/lm-000188/",
  "raw_url": "/raw/lm-000188.md",
  "api_url": "/api/papers/lm-000188.json",
  "legacy_page_url": "/papers/paper-161.md.html",
  "legacy_raw_url": "/papers/paper-161.md",
  "hash": "sha256:83a014df37fdec9644a3b19a9a7df7792256c9594b69587a877239e5d0582ce8"
}
