{
  "id": "lm-000874",
  "title": "統一博弈理論框架：從本質解到動態規則主導的完整體系",
  "source_file": "content/papers/2026/2026-05/統一博弈理論框架：從本質解到動態規則主導的完整體系.md",
  "legacy_slug": "paper-356.md",
  "ext": "md",
  "language": "zh-Hant",
  "created": "2026-05-09",
  "year": 2026,
  "month": "2026-05",
  "date_confidence": "explicit",
  "date_basis": "git-first-add (publication/upload date; not the author's in-text writing date)",
  "canonical_url": "/p/lm-000874/",
  "raw_url": "/raw/lm-000874.md",
  "api_url": "/api/papers/lm-000874.json",
  "legacy_page_url": "/papers/paper-356.md.html",
  "legacy_raw_url": "/papers/paper-356.md",
  "hash": "sha256:dd8ce26737aa79ba2e2680e7d7820839a648d13ce7e6aa5f9ee7b06710f01d66"
}
