{
  "id": "lm-000627",
  "title": "時代拓撲論_v1.0",
  "source_file": "content/papers/2026/2026-05/時代拓撲論_v1.0.md",
  "legacy_slug": "v1.0-1.md",
  "ext": "md",
  "language": "zh-Hant",
  "created": "2026-05-26",
  "year": 2026,
  "month": "2026-05",
  "date_confidence": "explicit",
  "date_basis": "git-first-add (publication/upload date; not the author's in-text writing date)",
  "canonical_url": "/p/lm-000627/",
  "raw_url": "/raw/lm-000627.md",
  "api_url": "/api/papers/lm-000627.json",
  "legacy_page_url": "/papers/v1.0-1.md.html",
  "legacy_raw_url": "/papers/v1.0-1.md",
  "hash": "sha256:e84dfeda5403ffa7574568985930b6dc157ba7f3aeb2563a3ced3c797b57e638"
}
