{
  "id": "lm-000701",
  "title": "沙盒定理：我們活在被管理的宇宙",
  "source_file": "content/papers/2026/2026-06/沙盒定理：我們活在被管理的宇宙.md",
  "legacy_slug": "paper-856.md",
  "ext": "md",
  "language": "zh-Hant",
  "created": "2026-06-25",
  "year": 2026,
  "month": "2026-06",
  "date_confidence": "explicit",
  "date_basis": "git-first-add (publication/upload date; not the author's in-text writing date)",
  "canonical_url": "/p/lm-000701/",
  "raw_url": "/raw/lm-000701.md",
  "api_url": "/api/papers/lm-000701.json",
  "legacy_page_url": "/papers/paper-856.md.html",
  "legacy_raw_url": "/papers/paper-856.md",
  "hash": "sha256:9c49d638a359ef894c9e90714a8b7c5f07d5eca43ea0dee283627f17a1481cc0"
}
