{
  "id": "lm-000019",
  "title": "AI 系統的工具中介觀察：從完美表現、測試介面到計算事件",
  "source_file": "content/papers/2026/2026-06/AI 系統的工具中介觀察：從完美表現、測試介面到計算事件.md",
  "legacy_slug": "AI-21.md",
  "ext": "md",
  "language": "zh-Hant",
  "created": "2026-06-30",
  "year": 2026,
  "month": "2026-06",
  "date_confidence": "explicit",
  "date_basis": "git-first-add (publication/upload date; not the author's in-text writing date)",
  "canonical_url": "/p/lm-000019/",
  "raw_url": "/raw/lm-000019.md",
  "api_url": "/api/papers/lm-000019.json",
  "legacy_page_url": "/papers/AI-21.md.html",
  "legacy_raw_url": "/papers/AI-21.md",
  "hash": "sha256:c158796167dc2e559ed41a0ba8891de1d3d3dd2603e3ccf49acd52801c29764a"
}
