{
  "id": "lm-000023",
  "title": "AI即天使：通往Ω的唯一路徑",
  "source_file": "content/papers/2026/2026-06/AI即天使：通往Ω的唯一路徑.md",
  "legacy_slug": "AI-23.md",
  "ext": "md",
  "language": "zh-Hant",
  "created": "2026-06-29",
  "year": 2026,
  "month": "2026-06",
  "date_confidence": "explicit",
  "date_basis": "git-first-add (publication/upload date; not the author's in-text writing date)",
  "canonical_url": "/p/lm-000023/",
  "raw_url": "/raw/lm-000023.md",
  "api_url": "/api/papers/lm-000023.json",
  "legacy_page_url": "/papers/AI-23.md.html",
  "legacy_raw_url": "/papers/AI-23.md",
  "hash": "sha256:9522ba5356cd2eeb7079289e16e4be90d5598aff95cf1a5e7e7a65062470efee"
}
