{
  "id": "lm-000451",
  "title": "對稱場消矩測積法：不規則圖形的非成像總量式面積量測原理",
  "source_file": "content/papers/2026/2026-06/對稱場消矩測積法：不規則圖形的非成像總量式面積量測原理.md",
  "legacy_slug": "paper-698.md",
  "ext": "md",
  "language": "zh-Hant",
  "created": "2026-06-22",
  "year": 2026,
  "month": "2026-06",
  "date_confidence": "explicit",
  "date_basis": "git-first-add (publication/upload date; not the author's in-text writing date)",
  "canonical_url": "/p/lm-000451/",
  "raw_url": "/raw/lm-000451.md",
  "api_url": "/api/papers/lm-000451.json",
  "legacy_page_url": "/papers/paper-698.md.html",
  "legacy_raw_url": "/papers/paper-698.md",
  "hash": "sha256:b0af166fa1cc5919eb58c2369a76597e57a5306a1e960964e5aca234caa7daba"
}
