{
  "id": "lm-000729",
  "title": "漢語「太X」詞族的湧現極限算子_從不可說到可說的間隙形式化",
  "source_file": "content/papers/2026/2026-06/漢語「太X」詞族的湧現極限算子_從不可說到可說的間隙形式化.md",
  "legacy_slug": "X-1.md",
  "ext": "md",
  "language": "zh-Hant",
  "created": "2026-06-17",
  "year": 2026,
  "month": "2026-06",
  "date_confidence": "explicit",
  "date_basis": "git-first-add (publication/upload date; not the author's in-text writing date)",
  "canonical_url": "/p/lm-000729/",
  "raw_url": "/raw/lm-000729.md",
  "api_url": "/api/papers/lm-000729.json",
  "legacy_page_url": "/papers/X-1.md.html",
  "legacy_raw_url": "/papers/X-1.md",
  "hash": "sha256:8cac2df9534e49e45e96dd312ebe0f0f86e9d84ee797b8ed43dd8045686183f4"
}
