{
  "id": "lm-000679",
  "title": "格點文明_方塊字與天圓地方的猜想",
  "source_file": "content/papers/2026/2026-06/格點文明_方塊字與天圓地方的猜想.md",
  "legacy_slug": "paper-843.md",
  "ext": "md",
  "language": "zh-Hant",
  "created": "2026-06-23",
  "year": 2026,
  "month": "2026-06",
  "date_confidence": "explicit",
  "date_basis": "git-first-add (publication/upload date; not the author's in-text writing date)",
  "canonical_url": "/p/lm-000679/",
  "raw_url": "/raw/lm-000679.md",
  "api_url": "/api/papers/lm-000679.json",
  "legacy_page_url": "/papers/paper-843.md.html",
  "legacy_raw_url": "/papers/paper-843.md",
  "hash": "sha256:68c337d201b0f4ea3d8169f78b33a47c79ef16078c74a84390e9d4bf011ba11b"
}
